gec_metrics/__init__.py
gec_metrics/cli/evaluate.py
gec_metrics/cli/gen_default_config.py
gec_metrics/cli/gen_gotoscorer_weight.py
gec_metrics/cli/gen_subset.py
gec_metrics/cli/m2_to_raw.py
gec_metrics/cli/prepare_meta_eval.py
gec_metrics/meta_eval/__init__.py
gec_metrics/meta_eval/base.py
gec_metrics/meta_eval/gjg.py
gec_metrics/meta_eval/gjg_test.py
gec_metrics/meta_eval/prepare_meta_eval.sh
gec_metrics/meta_eval/seeda.py
gec_metrics/meta_eval/seeda_test.py
gec_metrics/meta_eval/utils.py
gec_metrics/metrics/__init__.py
gec_metrics/metrics/base.py
gec_metrics/metrics/bertscore.py
gec_metrics/metrics/bertscore_test.py
gec_metrics/metrics/errant.py
gec_metrics/metrics/errant_test.py
gec_metrics/metrics/gleu.py
gec_metrics/metrics/gleu_test.py
gec_metrics/metrics/gotoscorer.py
gec_metrics/metrics/gotoscorer_test.py
gec_metrics/metrics/green.py
gec_metrics/metrics/green_test.py
gec_metrics/metrics/impara.py
gec_metrics/metrics/impara_test.py
gec_metrics/metrics/llm_kobayashi24.py
gec_metrics/metrics/pt_errant.py
gec_metrics/metrics/pt_errant_test.py
gec_metrics/metrics/scribendi.py
gec_metrics/metrics/scribendi_test.py
gec_metrics/metrics/some.py
gec_metrics/metrics/some_test.py
gec_metrics-0.1.1.dist-info/METADATA
gec_metrics-0.1.1.dist-info/WHEEL
gec_metrics-0.1.1.dist-info/entry_points.txt
gec_metrics-0.1.1.dist-info/licenses/LICENSE
gec_metrics-0.1.1.dist-info/RECORD
