Metadata-Version: 2.4
Name: gec-metrics
Version: 0.1.1
Summary: A library for Grammatical Error Correction evaluation.
Author: gotuiyan
License-File: LICENSE
Requires-Python: >=3.11.0
Requires-Dist: accelerate>=1.5.2
Requires-Dist: bert-score>=0.3.13
Requires-Dist: bitsandbytes>=0.45.3
Requires-Dist: datasets>=3.4.1
Requires-Dist: errant>=3.0.0
Requires-Dist: fuzzywuzzy>=0.18.0
Requires-Dist: gecommon>=0.1.0
Requires-Dist: openai>=1.68.0
Requires-Dist: outlines>=0.2.1
Requires-Dist: pandas>=2.2.3
Requires-Dist: python-levenshtein>=0.26.1
Requires-Dist: scipy>=1.14.1
Requires-Dist: seaborn>=0.13.2
Requires-Dist: sentencepiece>=0.2.0
Requires-Dist: torch>=2.5.1
Requires-Dist: transformers>=4.47.1
Requires-Dist: trueskill>=0.4.5
